difft/__init__.py
difft/attachment.py
difft/auth.py
difft/client.py
difft/command.py
difft/constants.py
difft/difft_ws_listener.py
difft/message.py
difft/utils.py
difftcc-1.0.0.dist-info/METADATA
difftcc-1.0.0.dist-info/WHEEL
difftcc-1.0.0.dist-info/entry_points.txt
difftcc-1.0.0.dist-info/top_level.txt
difftcc-1.0.0.dist-info/RECORD
