Metadata-Version: 2.1
Name: difftcc
Version: 1.0.0
Summary: Difft Openapi For CC
Home-page: UNKNOWN
Author: difft.org
Author-email: teams@difft.org
License: UNKNOWN
Platform: UNKNOWN
Requires-Python: >=3.6
Requires-Dist: requests
Requires-Dist: pycryptodome
Requires-Dist: websocket-client
Requires-Dist: rel
